[
  {
    "id": "txn_1761932094093_4rmb7ofvk",
    "metadata": {
      "bank": {
        "name": "Paystack-Titan",
        "id": 629,
        "slug": "titan-paystack"
      },
      "account_name": "DINNGSOFTWARE/ORJI MICHAEL",
      "account_number": "9950266099",
      "assigned": true,
      "currency": "NGN",
      "metadata": null,
      "active": true,
      "id": 35359415,
      "created_at": "2025-10-28T14:30:29.000Z",
      "updated_at": "2025-10-31T17:34:53.000Z",
      "assignment": {
        "integration": 1621620,
        "assignee_id": 315991648,
        "assignee_type": "Customer",
        "expired": false,
        "account_type": "PAY-WITH-TRANSFER-RECURRING",
        "assigned_at": "2025-10-31T17:34:53.835Z",
        "expired_at": null,
        "assignment_expires_at": null
      },
      "customer": {
        "id": 315991648,
        "first_name": "Michael",
        "last_name": "Orji",
        "email": "orjimichael2240@gmail.com",
        "customer_code": "CUS_zmb5em28zxtej5o",
        "phone": "08148863871",
        "metadata": {},
        "risk_action": "default",
        "international_format_phone": null
      }
    },
    "bankName": "Paystack-Titan",
    "bankId": 629,
    "bankSlug": "titan-paystack",
    "accountName": "DINNGSOFTWARE/ORJI MICHAEL",
    "accountNumber": "9950266099",
    "assigned": true,
    "currency": "NGN",
    "customerCode": "CUS_zmb5em28zxtej5o"
  }
]